aigs/__init__.py
aigs/games.py
aigs/types.py
aigs/utils.py
aigs-0.1.0.dist-info/METADATA
aigs-0.1.0.dist-info/WHEEL
aigs-0.1.0.dist-info/top_level.txt
aigs-0.1.0.dist-info/RECORD
