Metadata-Version: 2.4
Name: aigs
Version: 0.1.0
Summary: Package the Artificial Intelligence in Games and Simulation course
Requires-Python: <3.11,>=3.10
Requires-Dist: cma>=4.3.0
Requires-Dist: equinox>=0.12.2
Requires-Dist: flax>=0.10.7
Requires-Dist: grpcio>=1.73.0
Requires-Dist: gymnasium>=1.1.1
Requires-Dist: jax>=0.5.3
Requires-Dist: jaxlib>=0.5.3
Requires-Dist: jumanji>=1.1.1
Requires-Dist: mctx>=0.0.5
Requires-Dist: mlxp>=1.0.4
Requires-Dist: pettingzoo>=1.25.0
Requires-Dist: pgx>=2.6.0
Requires-Dist: pygame>=2.6.1
Requires-Dist: qdax>=0.5.0
Requires-Dist: tictactoe-gym>=1.0.1
Requires-Dist: torch>=2.7.1
Requires-Dist: transformers>=4.54.1
